{
  "generatedAt": "2026-04-24T07:51:59.570Z",
  "country": "Canada",
  "countryCode": "CA",
  "region": "North America",
  "repository": "HassanChowdhry/Canadian-Tech-Internships-2025",
  "totals": {
    "opportunities": 1,
    "openIssues": 1,
    "closedIssues": 0
  },
  "dataHash": "fdb93af88d2f2900bc2fafbee7dfb8e02bf1b810d6dee87ea1984646f4592583",
  "items": [
    {
      "id": "HassanChowdhry/Canadian-Tech-Internships-2025#7",
      "title": "README design and code style",
      "description": "- Make a banner for the repo, make it look nice\n- Add github pipeline to automatically change the README style to some standard format\n- Make a banner to thank contributers\n- Possibly get this SEO optimized",
      "excerpt": "- Make a banner for the repo, make it look nice - Add github pipeline to automatically change the README style to some standard format - Make a banner to thank contributers - Possibly get this SEO optimized",
      "issueState": "open",
      "contentHash": "47e2ade39d1825464202abf2b611b0beb8d556aedb5a18fa71080c620bfda299",
      "repository": "HassanChowdhry/Canadian-Tech-Internships-2025",
      "repositoryUrl": "https://github.com/HassanChowdhry/Canadian-Tech-Internships-2025",
      "region": "North America",
      "country": "Canada",
      "tags": [
        "enhancement"
      ],
      "author": {
        "id": "HassanChowdhry",
        "name": "HassanChowdhry",
        "handle": "HassanChowdhry",
        "avatarUrl": "https://avatars.githubusercontent.com/u/94680098?v=4"
      },
      "community": {
        "id": "HassanChowdhry",
        "name": "HassanChowdhry",
        "avatarUrl": "https://github.com/HassanChowdhry.png?size=80",
        "repository": "HassanChowdhry/Canadian-Tech-Internships-2025",
        "url": "https://github.com/HassanChowdhry/Canadian-Tech-Internships-2025"
      },
      "createdAt": "2024-09-11T14:55:17Z",
      "updatedAt": "2024-09-11T14:55:17Z",
      "url": "https://github.com/HassanChowdhry/Canadian-Tech-Internships-2025/issues/7",
      "sourceType": "github-issue"
    }
  ]
}
