{
  "generatedAt": "2026-07-14T13:15:07.986Z",
  "items": {
    "gh_a03d32efd2752d6d4c66083e": {
      "id": "gh_a03d32efd2752d6d4c66083e",
      "sourceId": "datascience-br/vagas#166",
      "title": "[Belo Horizonte/MG - Híbrido] Cientista de Dados na BHS",
      "description": "## Descrição da vaga\n\nProjeto em um cliente do segmento de engenharia civil, para atuação no time de Data Analytics.\n\nSuas atividades serão:\n· Interpretar todo universo de dados da empresa;\n· Criar, treinar e validar modelos preditivos e prescritivos utilizando técnicas de IA tradicional (como machine learning) e IA generativa (como deep learning);\n· Interpretar os resultados dos modelos e análises para gerar insights acionáveis que suportem a tomada de decisão estratégica;\n· Desenvolvimento de modelos preditivos utilizando técnicas estatísticas e algoritmos de aprendizado de máquina (ex.: regressão logística, gradient boosting e modelos aplicados a Marketing Mix Modeling – MMM);\n· Realização de análises exploratórias, testes de hipóteses e estudos analíticos para apoiar iniciativas de risco, marketing e tomada de decisão.\n· Participação na descoberta e no desenho de soluções de Marketing Mix Modeling (MMM), incluindo análise de fontes de dados, definição de variáveis de mídia e avaliação de estruturas estatísticas e bayesianas;\n· Automação de pipelines de dados e rotinas diárias de scoring em ambiente de nuvem;\n· Documentação de metodologias, métricas de validação, processos de monitoramento de desempenho e definições analíticas para iniciativas de modelagem;\n· Trabalho em parceria com equipes de negócios, marketing, engenharia e produto.\n\n## Local\n\nHíbrido/BH (2x na semana)\n\n## Benefícios\n\n- Plano de saúde e Assistência Odontológica;\n- Vale Refeição/Alimentação no cartão Flash;\n- Auxílio Híbrido;\n- Gympass / Wellhub;\n- Seguro de vida;\n- Licença Maternidade/Paternidade estendida;\n- Parcerias e convênios diversos em educação, saúde e lazer (Universidades, escolas de Idioma, academias, clínicas de saúde...);\n\n...\n## Requisitos\n\n#### Obrigatórios:\n\n· Graduação em Ciência da Computação ou áreas afins;\n· Google Cloud;\n· Big query;\n· Linguagem de programação Python;\n· MLOPS (de maneira geral);\n· Estatística clássica\n· Data pipelines;\n· Docker (Conteiners).\n\n#### Desejáveis:\n\n· Vertex e cortex;\n· Keras/tensorflow;\n· Pytorch;\n· Scikit;\n· Xgboosd;\n· Kedro;\n· Streamlit.\n\n\n## Contratação\n\n- CLT\n\n## Nossa empresa\n\nNós somos a BHS!\nCom 31 anos de experiência no mercado, proporcionamos soluções modernas de TI. 🚀\n\nSomos reconhecidos como a MELHOR empresa para se trabalhar em MG e TI do BRASIL pelo GPTW - Great Place to Work, e estamos classificados como a 4ª melhor empresa para se trabalhar na categoria LATAM.\n\n## Como se candidatar\n\n- https://bhs.gupy.io/jobs/11562751?jobBoardSource=gupy_public_page\n\n## Tempo médio de feedbacks\n\nCostumamos enviar feedbacks em até 10 dias após cada processo.\n\n## Labels\n<!-- retire os labels que não fazem sentido à vaga -->\n\n#### Alocação\n- Alocado\n- Hibrido\n\n#### Regime\n- CLT\n\n#### Nível\n\n- Sênior",
      "excerpt": "## Descrição da vaga Projeto em um cliente do segmento de engenharia civil, para atuação no time de Data Analytics. Suas atividades serão: · Interpretar todo universo de dados da empresa; · Criar, treinar e validar mo...",
      "issueState": "open",
      "contentHash": "ac00b30acbbb9ae2adaeb701987026be40cab03fa307a97905ed6ccf7b34bd5a",
      "repository": "datascience-br/vagas",
      "repositoryUrl": "https://github.com/datascience-br/vagas",
      "region": "South America",
      "country": "Brazil",
      "tags": [
        "python",
        "data"
      ],
      "author": {
        "id": "thothismybro",
        "name": "thothismybro",
        "handle": "thothismybro",
        "avatarUrl": "https://avatars.githubusercontent.com/u/118479053?v=4"
      },
      "community": {
        "id": "datascience-br",
        "name": "datascience-br",
        "avatarUrl": "https://github.com/datascience-br.png?size=80",
        "repository": "datascience-br/vagas",
        "url": "https://github.com/datascience-br/vagas"
      },
      "companyName": "BHS",
      "createdAt": "2026-07-14T12:53:20Z",
      "updatedAt": "2026-07-14T12:56:35Z",
      "url": "https://github.com/datascience-br/vagas/issues/166",
      "sourceType": "github-issue"
    },
    "gh_a0f4bab7589fd4825951c6df": {
      "id": "gh_a0f4bab7589fd4825951c6df",
      "sourceId": "awesome-jobs/vietnam#4761",
      "title": "Remote Fulltime - Up to $5000Net - Lead Backend Engineer (AI)",
      "description": "**Responsibilities**\n\n- Architect and design scalable and maintainable backend systems and APIs\n- Lead the development and implementation of backend features and functionalities\n- Collaborate with cross-functional teams to gather requirements and translate them into technical solutions\n- Mentor and guide junior backend engineers, fostering their technical growth and development\n- Optimize backend performance, ensuring high availability, reliability, and security\n- Integrate backend systems with external services and third-party APIs\n- Develop and maintain comprehensive documentation for backend systems and APIs\n- Participate in code reviews, ensuring code quality, best practices, and adherence to coding standards\n- Troubleshoot and debug complex backend issues, providing timely resolutions\n- Contribute to the overall technical strategy and roadmap of the backend systems\n\n\n**Technical Skills**\n\n- Strong proficiency in server-side programming languages such as Golang, Python, or Node.js\n- Expertise in designing and working with RESTful APIs and web services\n- Solid understanding of database systems, including relational databases (e.g., \n- MySQL, PostgreSQL and NoSQL databases (e.g., MongoDB, Cassandra), and proficiency in writing efficient and optimized database queries\n- Knowledge of server infrastructure, scalability, and deployment processes\n- Familiarity with containerization technologies like Docker, orchestration platforms like Kubernetes, and ability to work with cloud platforms such as AWS, Azure, or Google Cloud Platform\n- Experience with unit testing, integration testing, and API testing\n- Strong problem-solving skills and ability to debug complex systems\n- Excellent communication and collaboration skills, with the ability to work effectively in a team environment and proficiency in English\n\n**Please send your CV via**: Quynh.Thuy.Tran@navigossearch.com\nOr contact zalo/whatsapp: 0868272947",
      "excerpt": "**Responsibilities** - Architect and design scalable and maintainable backend systems and APIs - Lead the development and implementation of backend features and functionalities - Collaborate with cross-functional team...",
      "issueState": "open",
      "contentHash": "4f590e58fff5ebea2082cbbbf88fe216d55d19530617f0703efa7b2bb9343395",
      "repository": "awesome-jobs/vietnam",
      "repositoryUrl": "https://github.com/awesome-jobs/vietnam",
      "region": "Asia",
      "country": "Vietnam",
      "tags": [
        "remote",
        "backend",
        "node",
        "python",
        "golang",
        "junior",
        "data",
        "design"
      ],
      "author": {
        "id": "Queenietrann",
        "name": "Queenietrann",
        "handle": "Queenietrann",
        "avatarUrl": "https://avatars.githubusercontent.com/u/112934563?v=4"
      },
      "community": {
        "id": "awesome-jobs",
        "name": "awesome-jobs",
        "avatarUrl": "https://github.com/awesome-jobs.png?size=80",
        "repository": "awesome-jobs/vietnam",
        "url": "https://github.com/awesome-jobs/vietnam"
      },
      "createdAt": "2025-08-11T10:33:08Z",
      "updatedAt": "2026-06-02T08:22:52Z",
      "url": "https://github.com/awesome-jobs/vietnam/issues/4761",
      "sourceType": "github-issue"
    },
    "gh_a0d0697e0611db05ad0efa22": {
      "id": "gh_a0d0697e0611db05ad0efa22",
      "sourceId": "CangaceirosDevels/vagas_de_emprego#2797",
      "title": "[Remote] Backend Senior Developer Node.js and Javascript (Fluent English) - Hunter",
      "description": "Senior Developer Node.js and Javascript (Fluent English) only Brazil residents\n\nRemote.\n\nR$15k CLT.\n\nStays is the vacation rental software that increases your bookings on autopilot.\nOur solutions involve improving the performance of the Saas platform, as well as calendar management, task management, reservation management, payment gateways, messaging services, site builders, advanced API communications. We are a company at Despegar group\n\nWhat do you must have:\n\nMinimum of 7 years of professional software development experience\n\nAt least 5 years of hands-on experience with Node.js\n\nStrong Backend experience\n\nExperience with mongodb and Javascript\n\nFluent English\n\nExpericence requeried:\n\nNode.js, JavaScript (including closures, callbacks, promises, and async/await)\n\nMongoDB database (including schema design and optimization)\n\nAPI Design. Designing and implementing scalable and secure APIs.\n\nVersion Control. Advanced knowledge of Git, including branching strategies, pull requests, and code reviews.\n\nDevOps. CI/CD pipelines, containerization (Docker) and AWS cloud platform.\n\nTesting. Unit testing, integration testing using frameworks like Mocha, Jest, or similar.\n\nOur Benefits:\n\nhealth plan\n\nbonus\n\nfood allowance\n\nhome office allowance\n\nwellhub\n\n100% remote\n\nDay off.\n\n9h to 18h Brasília time zone.\n\nCompensation: R$15k CLT.\n\nSe tem interesse e os requisitos da oportunidade entre em contato pelo Linkedin abaixo, informando qual é a oportunidade:[https://www.linkedin.com/in/erickamarquesb/]",
      "excerpt": "Senior Developer Node.js and Javascript (Fluent English) only Brazil residents Remote. R$15k CLT. Stays is the vacation rental software that increases your bookings on autopilot. Our solutions involve improving the pe...",
      "issueState": "open",
      "contentHash": "8e9c5370c4beafdf3db486b39ae40fed46b17b516470622f786ac4737c64bc17",
      "repository": "CangaceirosDevels/vagas_de_emprego",
      "repositoryUrl": "https://github.com/CangaceirosDevels/vagas_de_emprego",
      "region": "South America",
      "country": "Brazil",
      "tags": [
        "clt"
      ],
      "author": {
        "id": "ErickaMB",
        "name": "ErickaMB",
        "handle": "ErickaMB",
        "avatarUrl": "https://avatars.githubusercontent.com/u/73557073?v=4"
      },
      "community": {
        "id": "CangaceirosDevels",
        "name": "CangaceirosDevels",
        "avatarUrl": "https://github.com/CangaceirosDevels.png?size=80",
        "repository": "CangaceirosDevels/vagas_de_emprego",
        "url": "https://github.com/CangaceirosDevels/vagas_de_emprego"
      },
      "salary": {
        "currency": "BRL",
        "min": 15000,
        "period": "month"
      },
      "createdAt": "2025-02-14T18:45:32Z",
      "updatedAt": "2025-02-14T18:45:56Z",
      "url": "https://github.com/CangaceirosDevels/vagas_de_emprego/issues/2797",
      "sourceType": "github-issue"
    },
    "gh_a087c2a7e4c36bd695c90fdc": {
      "id": "gh_a087c2a7e4c36bd695c90fdc",
      "sourceId": "Empregos-dev/Vagas-dev#93",
      "title": "🚀 Vaga Desenvolvedor Full-stack Junior (React.js + Node.js) 📍 remoto 🚀",
      "description": "# Desenvolvedor Full-stack Junior (React.js + Node.js)\n\n- 📍 Localização: remoto\n- 📈 Nível: junior\n- 📃 Contrato: pj\n- 💰 Salário: R$: 6.000,00\n- 🏃‍♂️ Corre para se candidatar, ainda dá tempo! 🕗\n\n\n## Descrição da vaga:\nO que é a Shaw and Partners? O que eles fazem? Onde vivem?\nShaw and Partners é uma fábrica de desenvolvimento de software americana para startups de alto nível, com aproximadamente 25 funcionários remotos. \nChristopher Shaw é o fundador e CEO.\n\n\n\n## Atividades e responsabilidade:\nO que você vai fazer: \n• Conceber, construir e manter código eficiente, reutilizável e fiável\n• Garantir o melhor desempenho possível, qualidade e capacidade de resposta das aplicações\n• Identificar e rastrear estrangulamentos e bugs, e conceber soluções para esses problemas\n• Ajudar a manter a qualidade do código, a organização e os padrões internos\n\n\n## Requisitos:\nO que você precisa saber e trazer na bagagem: \n• Frustração com códigos mal construídos, ineficientes e insustentáveis\n• Experiência em consumir APIs de back-end e front-end com foco no usuário\n• Conhecimentos fundamentais e sólidos em Ciência da Computação (algoritmos, estrutura de dados, concorrência, etc.\n• Conhecimento em React.js, Node.js e TypeScript\n\nE seria muito legal se você tiver:\n• Forte experiência e interesse em trabalhar com Kubernetes, Amazon Web Services, Google Cloud Platform\n• Experiência com Next e Responsive Web Design, padrões e soluções de gestão de estados (por exemplo, Redux) ES2015+, APIs HTML5 e CSS3\n• Experiência de trabalho em integração/implantação contínua\n\n\n\n\n\n\n## Mais Informações:\nMas, antes de você se candidatar precisa saber que: \n• Terá a oportunidade de trabalhar bem próximo do nosso CEO, relaxa ele não morde\n• Nós te pagamos em USD \n• Aqui a gente não te pede inglês avançado para guardar na gaveta, temos funcionários da Jordânia, Egito, Argentina, Brasil, Estados Unidos, Ucrânia e entre outros. \n• Não temos happy hour às sextas porque todos trabalham remotamente, mas tem joguinho online se marcar com a equipe \n• Tem médico ou prova para tirar carteira de motorista no meio da semana? Não tem problema, você mesmo gerencia suas horas, só precisa ficar atento quando o cliente manda mensagem e solicita uma reunião. \n• Parece ser meio óbvio, mas pra quem nunca trabalhou no modelo remoto, nós não exigimos dresscode. Só não pode aparecer sem camiseta quando rolar uma vídeo chamada, combinado?\n• Se você indica um coleguinha para trabalhar conosco e a pessoa é contratada, após três meses de contrato de trabalho do seu amigo, a gente te paga uma mesada\n• Não somos o Google, mas nosso processo seletivo é bem rápido do que os dele, pode confiar\n\nTeremos um crush por você se:\n• Ter senso de dono, o projeto é seu, rolou um bug no final de semana? Concerte\n• Curte trabalhar no projeto do início ao fim, então arregace as mangas porque você vai trabalhar tanto em front-end como em back-end também. Mas não se preocupe se você não gosta tanto assim de trabalhar com um dos dois, conta pra gente que damos um jeito!\n• Gosta de trabalhar em equipe, “ninguém solta a mão de ninguém”\n• Tá ligado nas novidades do mundo tech e gosta de dar “pitaco” com novas ideias e soluções\n• Está sempre atento ao feedback do cliente, afinal é ele que paga as contas\n\nTalvez a Shaw a não seja a empresa certa para você se: \n• É uma pessoa preguiçosa hahaha \n• Precisa de micro gerenciamento. Claro que sabemos que um profissional júnior precisará de um pouco mais de atenção no início, mas depois que “você aprende a andar de bicicleta”, não esquece nunca mais, né?\n• Quer trabalhar em uma empresa 100% segura e busca total estabilidade. Somos uma startup em crescimento avançado\n\n\n# [🔗 Clique aqui para se candidatar](https://empregos.dev/vaga/desenvolvedor-full-stack-junior-reactjs-nodejs-8619)\n\n\n**Use nosso site [Empregos.dev](https://empregos.dev) para buscar mais vagas de trabalho na área da programação, desenvolvimento, devops e tecnologia como está!**",
      "excerpt": "# Desenvolvedor Full-stack Junior (React.js + Node.js) - 📍 Localização: remoto - 📈 Nível: junior - 📃 Contrato: pj - 💰 Salário: R$: 6.000,00 - 🏃‍♂️ Corre para se candidatar, ainda dá tempo! 🕗 ## Descrição da vaga...",
      "issueState": "open",
      "contentHash": "bee5b293a441710b608a3cb94bef7989ad3d4dfe8a6fcc211d181a1c2045be94",
      "repository": "Empregos-dev/Vagas-dev",
      "repositoryUrl": "https://github.com/Empregos-dev/Vagas-dev",
      "region": "South America",
      "country": "Brazil",
      "tags": [
        "node.js",
        "remoto",
        "pj",
        "junior"
      ],
      "author": {
        "id": "ecossistemadev",
        "name": "ecossistemadev",
        "handle": "ecossistemadev",
        "avatarUrl": "https://avatars.githubusercontent.com/u/107730006?v=4"
      },
      "community": {
        "id": "Empregos-dev",
        "name": "Empregos-dev",
        "avatarUrl": "https://github.com/Empregos-dev.png?size=80",
        "repository": "Empregos-dev/Vagas-dev",
        "url": "https://github.com/Empregos-dev/Vagas-dev"
      },
      "createdAt": "2025-01-21T20:29:10Z",
      "updatedAt": "2025-01-21T20:29:10Z",
      "url": "https://github.com/Empregos-dev/Vagas-dev/issues/93",
      "sourceType": "github-issue"
    }
  }
}
