{
  "generatedAt": "2026-04-25T01:48:13.287Z",
  "items": {
    "gh_f2100cea776c8f26b7ce2d10": {
      "id": "gh_f2100cea776c8f26b7ce2d10",
      "sourceId": "qa-brasil/vagas#1240",
      "title": "[São Paulo/SP] QA Pleno na Loop",
      "description": "## Descrição da vaga\n\nBuscamos um Analista de QA Pleno para atuar de forma autônoma no ciclo de vida do desenvolvimento de software. Você será o guardião da qualidade, responsável por planejar e executar testes, com foco na expansão e manutenção da nossa cobertura de automação. Se você tem conhecimento sólido em automação e sabe como mitigar riscos de forma proativa, garantindo a integridade dos nossos sistemas de alto volume transacional, esta vaga é para você.\n\n### Principais Responsabilidades\n\n- Desenhar, implementar e executar estratégias de testes (funcionais, regressão, integração e exploratórios) para garantir a qualidade das entregas.\n- Desenvolver e manter frameworks de automação de testes (Web, Mobile e API).\n- Integrar testes automatizados em pipelines de CI/CD para garantir a entrega contínua.\n- Identificar, analisar e documentar bugs de forma clara, colaborando com o time de desenvolvimento para a rápida correção.\n- Colaborar ativamente com equipes multidisciplinares: Desenvolvedores (Devs), Gerentes de Produto (PMs), Designers de UX/UI e outros QAs.\n- Mapear riscos de qualidade e priorizar testes com base nos objetivos do negócio e no impacto para o usuário.\n\n## Local de trabalho\n- Híbrido. O trabalho na Loop inclui funções remotas e no escritório em São Paulo/SP - Água Funda.\n\n## Requisitos da vaga\n\n**Obrigatórios**\n- Experiência sólida (mínimo de 3 anos) em Quality Assurance e testes de software.\n- Domínio na criação e execução de planos e estratégias de testes.\n- Experiência comprovada em automação de testes (Web, Mobile ou API) utilizando ferramentas/frameworks como Selenium, Cypress, Playwright, Appium, ou similares.\n- Conhecimento em linguagens de programação relevantes para automação (ex: Python, Java, JavaScript, C#).\n- Conhecimento e prática em testes de APIs REST/SOAP (utilizando ferramentas como Postman, SoapUI ou código).\n- Habilidade para identificar, documentar e rastrear bugs de forma clara e concisa (utilizando ferramentas como Jira, Azure DevOps ou similares).\n- Familiaridade com metodologias ágeis (Scrum, Kanban).\n- Comunicação Analítica: Habilidade para apresentar resultados de testes, métricas e riscos de forma clara e embasada para as equipes e stakeholders.\n- Proatividade e autonomia para gerenciar e entregar suas atividades com supervisão ocasional.\n\n**Desejáveis**\n- Conhecimento em testes de performance/carga (ex: k6, JMeter, LoadRunner) e segurança (ex: OWASP Top 10).\n- Familiaridade com conceitos de BDD/TDD (Behavior-Driven Development / Test-Driven Development).\n- Diferencial Inovador: Experiência ou forte interesse em aplicar Inteligência Artificial (IA) para aumentar a eficiência e a qualidade dos processos de QA (ex: geração de dados de teste, análise preditiva de falhas, otimização de suítes de teste).\n- Certificações na área de testes (ex: CTFL, CTAL).\n\n**Diferenciais**\n- Experiência em integração de testes em pipelines de CI/CD (ex: Jenkins, GitLab CI, GitHub Actions).\n\n## Forma de contratação\n\nPJ\n\n## Benefícios da empresa\n\n- 30 dias de descanso remunerado\n\n## Range Salarial\nA vaga paga entre 5.000,00 e 6.500,00 reais.\n\n## Sobre a empresa\n\nPara quem compra ou vende um veículo, existe sempre a busca pelo bom negócio. Somos tecnologia, processos e pessoas dedicados a melhorar nossos serviços para que o seu negócio aconteça. Fazemos tudo: remoção, vistoria, anúncio, negociação, transferência, documentação, financiamento, seguro, logística, recebimento e pagamento.\n\nA Loop é uma empresa do grupo Webmotors e Santander fundada em 2014, já efetuamos a venda de mais de 85 mil veículos e realizamos mais de 2.500 eventos de comercialização com presença em todo o Brasil com mais de 9 unidades. Com esta estrutura podemos atender todos os públicos tanto empresas na composição de estoque e desmobilização de frotas ou pessoas físicas em busca de comprar ou vender veículos.\n\n## Como se candidatar\n\nPor favor envie um email para [t.william.espindola@loopbrasil.com](mailto:t.william.espindola@loopbrasil.com) com seu CV anexado ou Linkedin atualizado: QA Pleno na Loop\n\n## Tempo médio de feedbacks\n\nCostumamos enviar feedbacks em até 5 dias após cada processo.\n\nE-mail para contato em caso de não haver resposta: [t.william.espindola@loopbrasil.com](mailto:t.william.espindola@loopbrasil.com)\n\n## Labels\n<!-- Label é uma forma dos QAs conseguirem pesquisar as vagas. Após cadastrar a vaga, ela receberá label automaticamente em até 2 minutos.\nApague os itens abaixo que não corresponderem à vaga. -->\n- PJ\n- Pleno\n- Presencial\n- Remoto\n- São Paulo/SP",
      "excerpt": "## Descrição da vaga Buscamos um Analista de QA Pleno para atuar de forma autônoma no ciclo de vida do desenvolvimento de software. Você será o guardião da qualidade, responsável por planejar e executar testes, com fo...",
      "issueState": "open",
      "contentHash": "b629fc0077269e826f298fa50e6d6a394ec5c6cd6a5aab18bfb5b93cb5aabdfb",
      "repository": "qa-brasil/vagas",
      "repositoryUrl": "https://github.com/qa-brasil/vagas",
      "region": "South America",
      "country": "Brazil",
      "tags": [
        "pj",
        "pleno",
        "remoto",
        "são paulo",
        "presencial",
        "stale"
      ],
      "author": {
        "id": "williamespindola",
        "name": "williamespindola",
        "handle": "williamespindola",
        "avatarUrl": "https://avatars.githubusercontent.com/u/794521?v=4"
      },
      "community": {
        "id": "qa-brasil",
        "name": "qa-brasil",
        "avatarUrl": "https://github.com/qa-brasil.png?size=80",
        "repository": "qa-brasil/vagas",
        "url": "https://github.com/qa-brasil/vagas"
      },
      "companyName": "30 dias de descanso remunerado",
      "createdAt": "2026-01-08T03:21:57Z",
      "updatedAt": "2026-04-18T02:49:39Z",
      "url": "https://github.com/qa-brasil/vagas/issues/1240",
      "sourceType": "github-issue"
    },
    "gh_f28cafadf67bee6ce31dc175": {
      "id": "gh_f28cafadf67bee6ce31dc175",
      "sourceId": "3Tecnos-Development/vagas#7",
      "title": "[Hibrido/Remota - Brusque] Dev Python na Maior Loja de Departamentos do #BRASIL 🗽",
      "description": "Estou com uma SUPER oportunidade para atuar como Desenvolvedor Python na MAIOR loja de departamentos do #BRASIL 🗽 com um ambiente inovador e transformador \n==================================================\n\n## Descrição da vaga\n\nSe você curte tecnologia, programação e novos desafios a vaga é para você! Somos um time de profissionais voltados para diversas áreas da tecnologia como Data Science, DevOps, User Experience, Database entre muitas outras frentes focadas na inovação digital de uma das gigantes varejistas do Brasil.\nNosso objetivo é desenvolver soluções inovadoras para clientes, fornecedores e os mais de 20 mil colaboradores. Aqui descomplicamos tudo através de uma metodologia ágil e juntos já fizemos acontecer centenas de projetos com reconhecimento nacional e internacional de RFID, Inteligência Artificial, aplicativos entre outros.\n\n## Local\n\nRemoto, mas contamos com um espaço exclusivo no Centro de Inovação, em Brusque (SC).\n\n## Requisitos\n\n**Obrigatórios:**\n- APIs Restful utilizando Python;\n- Conhecimento sobre formatos de tráfego de dados (json, XML, etc);\n- Familiaridade com tecnologias web;\n- Experiência sólida em desenvolvimento com Python;\n- Experiência com integrações REST Conhecimento em base de dados SQL Lite ou Realm.\n- Versionamento de código Git.\n- Conhecimento básico em testes unitários e de interface.\n- Flexibilidade em consumir e manipular dados de fontes diversas: APIs, banco de dados, web services, planilhas, etc.\n- Fácil adaptação em ambientes colaborativos, e que comprometa-se com a equipe e os prazos estabelecidos.\n- Conhecimento intermediário/avançado sobre SQL; Conhecimento sobre formatos de tráfego de dados (json, XML, etc).\n\n**Diferenciais:**\n- Tempo de experiência em programação Python (pelo menos dois anos).\n- Experiência com bancos de dados relacionais e não relacional.\n- Conhecimentos em Git e Docker.\n- Conhecimento em Elasticsearch.\n- Conhecimento em JSON, serialização / desserialização.\n- Conhecimento em Airflow.\n\n## Benefícios\n\n- Vale refeição ou alimentação - R$410,00 ALELO - desconta 20%\n- Ajuda de Custo Home Office - R$100,00;\n- Vale transporte - 6% previsto lei\n- PPR - anual - corresponde ao 14º salário\n- Convênio SESC\n- Convênio com escola\n- Plano Unimed (Por adesão) - plano regional e nacional - coparticipação de 50%\n- Empresa cidadã (licença maternidade de 6 meses e paternidade de 20 dias)\n- Banco de horas\n- Oportunidades de crescimento\n\n## Contratação\n\nCLT\n\n## Como se candidatar\n\nPor favor envie um email para cintia.kleine@gruposelecionar.com.br com seu CV anexado\nMe chame no linkedin [Cintia Kleine](https://www.linkedin.com/in/cintiakleine2607/)\nOu me adicione no [Whats](https://api.whatsapp.com/send?phone=5547997653031)\n\n## Tempo médio de feedbacks\n\nCostumamos enviar feedbacks entre 3 a 5 dias após cada processo.\n\n## Labels\n\n- 🏢 Flexível\n- 🏢 Presencial\n- 🏢 Remoto\n- 👨 Pleno\n- 👴 Sênior",
      "excerpt": "Estou com uma SUPER oportunidade para atuar como Desenvolvedor Python na MAIOR loja de departamentos do #BRASIL 🗽 com um ambiente inovador e transformador ================================================== ## Descriç...",
      "issueState": "open",
      "contentHash": "663d6d07ad2953d041cca95e7886a78f5c14abc9d81888d3eb09e3d48037cc4b",
      "repository": "3Tecnos-Development/vagas",
      "repositoryUrl": "https://github.com/3Tecnos-Development/vagas",
      "region": "South America",
      "country": "Brazil",
      "tags": [
        "python",
        "pleno",
        "devops",
        "data"
      ],
      "author": {
        "id": "ghost",
        "name": "ghost",
        "handle": "ghost",
        "avatarUrl": "https://avatars.githubusercontent.com/u/10137?v=4"
      },
      "community": {
        "id": "3Tecnos-Development",
        "name": "3Tecnos-Development",
        "avatarUrl": "https://github.com/3Tecnos-Development.png?size=80",
        "repository": "3Tecnos-Development/vagas",
        "url": "https://github.com/3Tecnos-Development/vagas"
      },
      "createdAt": "2021-07-01T12:20:57Z",
      "updatedAt": "2021-07-01T12:20:57Z",
      "url": "https://github.com/3Tecnos-Development/vagas/issues/7",
      "sourceType": "github-issue"
    }
  }
}
